{"type":"Topology","objects":{"sfmta":{"type":"GeometryCollection","geometries":[{"type":"LineString","properties":{"PREDOMINAN":"MC"},"id":"WEEKDAY","arcs":[0,1,2]},{"type":"MultiLineString","properties":{"PREDOMINAN":"MC"},"id":"WEEKDAY","arcs":[[3],[4],[-2,5]]},{"type":"LineString","properties":{"PREDOMINAN":"MC"},"id":"SATURDAY","arcs":[-3,-2,-1]},{"type":"MultiLineString","properties":{"PREDOMINAN":"MC"},"id":"SATURDAY","arcs":[[3],[4],[-6,1]]},{"type":"LineString","properties":{"PREDOMINAN":"MC"},"id":"SUNDAY","arcs":[0,1,2]},{"type":"MultiLineString","properties":{"PREDOMINAN":"MC"},"id":"SUNDAY","arcs":[[3],[-2,5],[4]]}]}},"arcs":[[[4194,1243],[0,31],[643,-13],[655,-18]],[[5492,1243],[109,572],[107,580],[119,615],[49,330],[131,4],[548,154],[691,198],[262,70],[394,-9],[143,734],[36,35],[95,49],[131,17],[274,18],[71,4],[191,22],[405,62],[251,22],[225,4],[132,31],[47,39],[37,194],[11,35],[24,26],[24,163],[-35,66],[24,167],[-108,0],[-297,13],[-107,26],[-382,141],[-118,62],[-59,281],[-1002,-26],[-2001,-57],[-107,492],[-153,795],[-48,198],[-95,537],[-107,514],[-165,791],[-167,787],[-1132,-31],[-1131,-35]],[[2809,9933],[-585,-17],[-548,-14],[-548,-17],[-441,18]],[[639,9903],[-94,-36],[165,-786]],[[2813,9933],[165,-789],[-587,-17],[-550,-16],[-546,-15],[-585,-17]],[[5492,1243],[644,-13],[643,-18],[643,-13],[691,211],[345,-167],[-83,4],[-2013,-479],[-1013,-241],[-810,-189],[-954,-176],[-1059,-109],[-941,-49],[-1585,-4],[12,233],[96,70],[167,35],[142,5],[870,-22],[500,-9],[394,9],[262,22],[309,70],[309,31],[644,56],[190,45],[96,44],[83,74],[120,580]]],"transform":{"scale":[9.616960447032545e-7,0.0000020300029572350945],"translate":[-122.41897099900608,37.73220899973887]}}